pilio/__init__.py
pilio/main.py
pilio/pilio_types.py
pilio-0.1.5.dist-info/METADATA
pilio-0.1.5.dist-info/WHEEL
pilio-0.1.5.dist-info/RECORD
