Metadata-Version: 2.1
Name: pilio
Version: 0.1.5
Summary: 
Author: Ivan Zhang
Author-email: ivanzhangofficial@gmail.com
Requires-Python: >=3.8,<4.0
Classifier: Programming Language :: Python :: 3
Classifier: Programming Language :: Python :: 3.8
Classifier: Programming Language :: Python :: 3.9
Classifier: Programming Language :: Python :: 3.10
Classifier: Programming Language :: Python :: 3.11
Classifier: Programming Language :: Python :: 3.12
Requires-Dist: fastapi[standard] (>=0.114.2,<0.115.0)
Requires-Dist: requests (>=2.32.3,<3.0.0)
